{
    // Use IntelliSense to learn about possible attributes.
    // Hover to view descriptions of existing attributes.
    // For more information, visit: https://go.microsoft.com/fwlink/?linkid=830387
    "version": "0.2.0",
    "configurations": [

        {
            "command": "cross-env NODE_ENV=development PORT=3000 UPTIME_KUMA_HOST=0.0.0.0 && cd uptime-kuma/ && npm run start-server",
            "name": "start-server",
            "request": "launch",
            "type": "node-terminal",
        }
    ]
}